{
    "scores_files": [
        {
            "class": "File",
            "location": "/Users/kot4or/temp/mulloy/latest/chip/bigwigs/average/flag_mll_af4_set_1_3_average.bigWig"
        },
        {
            "class": "File",
            "location": "/Users/kot4or/temp/mulloy/latest/chip/bigwigs/average/flag_mll_af9_set_1_3_average.bigWig"
        }
    ],
    "scores_labels": [
        "FLAG MLL-AF4 signal",
        "FLAG MLL-AF9 signal"
    ],
    "regions_files":[
        {
            "class": "File",
            "location": "/Users/kot4or/temp/mulloy/latest/chip/peaks_sorted_by_asc_conc_from_diffbind/AF4_peaks.tsv"
        },
        {
            "class": "File",
            "location": "/Users/kot4or/temp/mulloy/latest/chip/peaks_sorted_by_asc_conc_from_diffbind/AF9_peaks.tsv"
        }
    ],
    "regions_labels": [
        "MLL-AF4 peaks",
        "MLL-AF9 peaks"
    ],
    "recentering": "Peak Center",
    "before_region_start_length": 5000,
    "after_region_start_length": 5000,
    "bin_size": 10,
    "plot_type": "lines",
    "what_to_show": "plot, heatmap and colorbar",
    "per_group": true,
    "threads": 10
}
